share_nb/__init__.py
share_nb-0.1.5.data/data/etc/jupyter/jupyter_notebook_config.d/share_nb.json
share_nb-0.1.5.dist-info/DESCRIPTION.rst
share_nb-0.1.5.dist-info/METADATA
share_nb-0.1.5.dist-info/RECORD
share_nb-0.1.5.dist-info/WHEEL
share_nb-0.1.5.dist-info/metadata.json
share_nb-0.1.5.dist-info/top_level.txt
